{
  "manifestVersion": "3.2",
  "proxies": [
    {
      "address": "0x91d5181101c41996d3A466F733b01A8050Fd3866",
      "txHash": "0x125a8a43101cd34192650409a1ecb67147afe64be8e3c52785edf4259398fc8c",
      "kind": "transparent"
    }
  ],
  "impls": {
    "472c056c09b2c2bba804837b8870cf765e7f0273c13567127dba807fe19ed08f": {
      "address": "0x7C75ca525F2070119f70549d93811f45E491eB3F",
      "txHash": "0x76e7e8bbc961e2909016eace83c3bd883de6d87527f56bb609997f5c67fa6042",
      "layout": {
        "solcVersion": "0.8.20",
        "storage": [
          {
            "label": "message",
            "offset": 0,
            "slot": "0",
            "type": "t_string_storage",
            "contract": "Swisstronik",
            "src": "contracts/Hello_swtr.sol:5"
          }
        ],
        "types": {
          "t_string_storage": {
            "label": "string",
            "numberOfBytes": "32"
          }
        },
        "namespaces": {}
      }
    }
  }
}
